pyol/__init__.py
pyol/hints.py
pyol/learning_rates.py
pyol/oco.py
pyol/projections.py
pyol/reductions.py
pyol/saddle_point.py
PyOL-0.0.3.dist-info/LICENSE
PyOL-0.0.3.dist-info/METADATA
PyOL-0.0.3.dist-info/WHEEL
PyOL-0.0.3.dist-info/top_level.txt
PyOL-0.0.3.dist-info/RECORD
