Metadata-Version: 2.1
Name: PyOL
Version: 0.0.3
Summary: A Python library for online learning
Home-page: https://github.com/bremen79/pyol
Author: Francesco Orabona
Author-email: francesco@orabona.com
License: UNKNOWN
Platform: UNKNOWN
Classifier: License :: OSI Approved :: GNU General Public License v3 (GPLv3)
Classifier: Programming Language :: Python :: 3
Classifier: Intended Audience :: Science/Research
Classifier: Topic :: Scientific/Engineering
Classifier: Operating System :: OS Independent
License-File: LICENSE
Requires-Dist: numpy
